[
 {
	"communityBoard": "101",
	"count": 583,
	"Failure to Comply": 29,
	"Miscellaneous": 84,
	"Building Maintenance": 69,
	"Elevator Maintenance": 33,
	"Work Without Permit": 33,
	"Other": 335
 },
 {
	"communityBoard": "102",
	"count": 795,
	"Failure to Comply": 87,
	"Miscellaneous": 100,
	"Building Maintenance": 86,
	"Elevator Maintenance": 21,
	"Work Without Permit": 77,
	"Other": 424
 },
 {
	"communityBoard": "103",
	"count": 896,
	"Failure to Comply": 74,
	"Miscellaneous": 92,
	"Building Maintenance": 152,
	"Elevator Maintenance": 61,
	"Work Without Permit": 79,
	"Other": 438
 },
 {
	"communityBoard": "104",
	"count": 866,
	"Failure to Comply": 54,
	"Miscellaneous": 96,
	"Building Maintenance": 146,
	"Elevator Maintenance": 42,
	"Work Without Permit": 64,
	"Other": 464
 },
 {
	"communityBoard": "105",
	"count": 1124,
	"Failure to Comply": 57,
	"Miscellaneous": 128,
	"Building Maintenance": 84,
	"Elevator Maintenance": 68,
	"Work Without Permit": 75,
	"Other": 712
 },
 {
	"communityBoard": "106",
	"count": 694,
	"Failure to Comply": 48,
	"Miscellaneous": 75,
	"Building Maintenance": 110,
	"Elevator Maintenance": 35,
	"Work Without Permit": 67,
	"Other": 359
 },
 {
	"communityBoard": "107",
	"count": 904,
	"Failure to Comply": 56,
	"Miscellaneous": 104,
	"Building Maintenance": 147,
	"Elevator Maintenance": 77,
	"Work Without Permit": 75,
	"Other": 445
 },
 {
	"communityBoard": "108",
	"count": 877,
	"Failure to Comply": 63,
	"Miscellaneous": 97,
	"Building Maintenance": 148,
	"Elevator Maintenance": 48,
	"Work Without Permit": 70,
	"Other": 451
 },
 {
	"communityBoard": "109",
	"count": 622,
	"Failure to Comply": 48,
	"Miscellaneous": 41,
	"Building Maintenance": 103,
	"Elevator Maintenance": 94,
	"Work Without Permit": 36,
	"Other": 300
 },
 {
	"communityBoard": "110",
	"count": 786,
	"Failure to Comply": 54,
	"Miscellaneous": 53,
	"Building Maintenance": 134,
	"Elevator Maintenance": 135,
	"Work Without Permit": 38,
	"Other": 372
 },
 {
	"communityBoard": "111",
	"count": 682,
	"Failure to Comply": 41,
	"Miscellaneous": 49,
	"Building Maintenance": 143,
	"Elevator Maintenance": 81,
	"Work Without Permit": 35,
	"Other": 333
 },
 {
	"communityBoard": "112",
	"count": 737,
	"Failure to Comply": 28,
	"Miscellaneous": 38,
	"Building Maintenance": 149,
	"Elevator Maintenance": 114,
	"Work Without Permit": 46,
	"Other": 362
 },
 {
	"communityBoard": "164",
	"count": 0,
	"Failure to Comply": 0,
	"Miscellaneous": 0,
	"Building Maintenance": 0,
	"Elevator Maintenance": 0,
	"Work Without Permit": 0,
	"Other": 0
 },
 {
	"communityBoard": "201",
	"count": 621,
	"Failure to Comply": 34,
	"Miscellaneous": 58,
	"Building Maintenance": 97,
	"Elevator Maintenance": 68,
	"Work Without Permit": 49,
	"Other": 315
 },
 {
	"communityBoard": "202",
	"count": 319,
	"Failure to Comply": 11,
	"Miscellaneous": 23,
	"Building Maintenance": 82,
	"Elevator Maintenance": 38,
	"Work Without Permit": 20,
	"Other": 145
 },
 {
	"communityBoard": "203",
	"count": 523,
	"Failure to Comply": 16,
	"Miscellaneous": 45,
	"Building Maintenance": 101,
	"Elevator Maintenance": 83,
	"Work Without Permit": 37,
	"Other": 241
 },
 {
	"communityBoard": "204",
	"count": 976,
	"Failure to Comply": 88,
	"Miscellaneous": 85,
	"Building Maintenance": 141,
	"Elevator Maintenance": 117,
	"Work Without Permit": 80,
	"Other": 465
 },
 {
	"communityBoard": "205",
	"count": 987,
	"Failure to Comply": 56,
	"Miscellaneous": 96,
	"Building Maintenance": 156,
	"Elevator Maintenance": 133,
	"Work Without Permit": 78,
	"Other": 468
 },
 {
	"communityBoard": "206",
	"count": 698,
	"Failure to Comply": 30,
	"Miscellaneous": 56,
	"Building Maintenance": 125,
	"Elevator Maintenance": 69,
	"Work Without Permit": 51,
	"Other": 367
 },
 {
	"communityBoard": "207",
	"count": 906,
	"Failure to Comply": 47,
	"Miscellaneous": 91,
	"Building Maintenance": 126,
	"Elevator Maintenance": 136,
	"Work Without Permit": 68,
	"Other": 438
 },
 {
	"communityBoard": "208",
	"count": 444,
	"Failure to Comply": 31,
	"Miscellaneous": 47,
	"Building Maintenance": 48,
	"Elevator Maintenance": 53,
	"Work Without Permit": 46,
	"Other": 219
 },
 {
	"communityBoard": "209",
	"count": 530,
	"Failure to Comply": 27,
	"Miscellaneous": 31,
	"Building Maintenance": 96,
	"Elevator Maintenance": 74,
	"Work Without Permit": 65,
	"Other": 237
 },
 {
	"communityBoard": "210",
	"count": 343,
	"Failure to Comply": 7,
	"Miscellaneous": 32,
	"Building Maintenance": 64,
	"Elevator Maintenance": 13,
	"Work Without Permit": 79,
	"Other": 148
 },
 {
	"communityBoard": "211",
	"count": 494,
	"Failure to Comply": 33,
	"Miscellaneous": 49,
	"Building Maintenance": 83,
	"Elevator Maintenance": 43,
	"Work Without Permit": 68,
	"Other": 218
 },
 {
	"communityBoard": "212",
	"count": 599,
	"Failure to Comply": 33,
	"Miscellaneous": 39,
	"Building Maintenance": 100,
	"Elevator Maintenance": 52,
	"Work Without Permit": 77,
	"Other": 298
 },
 {
	"communityBoard": "226",
	"count": 1,
	"Failure to Comply": 1,
	"Miscellaneous": 0,
	"Building Maintenance": 0,
	"Elevator Maintenance": 0,
	"Work Without Permit": 0,
	"Other": 0
 },
 {
	"communityBoard": "227",
	"count": 0,
	"Failure to Comply": 0,
	"Miscellaneous": 0,
	"Building Maintenance": 0,
	"Elevator Maintenance": 0,
	"Work Without Permit": 0,
	"Other": 0
 },
 {
	"communityBoard": "228",
	"count": 0,
	"Failure to Comply": 0,
	"Miscellaneous": 0,
	"Building Maintenance": 0,
	"Elevator Maintenance": 0,
	"Work Without Permit": 0,
	"Other": 0
 },
 {
	"communityBoard": "301",
	"count": 1539,
	"Failure to Comply": 50,
	"Miscellaneous": 215,
	"Building Maintenance": 157,
	"Elevator Maintenance": 130,
	"Work Without Permit": 146,
	"Other": 841
 },
 {
	"communityBoard": "302",
	"count": 904,
	"Failure to Comply": 29,
	"Miscellaneous": 136,
	"Building Maintenance": 74,
	"Elevator Maintenance": 115,
	"Work Without Permit": 58,
	"Other": 492
 },
 {
	"communityBoard": "303",
	"count": 1012,
	"Failure to Comply": 58,
	"Miscellaneous": 115,
	"Building Maintenance": 132,
	"Elevator Maintenance": 58,
	"Work Without Permit": 104,
	"Other": 545
 },
 {
	"communityBoard": "304",
	"count": 780,
	"Failure to Comply": 35,
	"Miscellaneous": 89,
	"Building Maintenance": 99,
	"Elevator Maintenance": 28,
	"Work Without Permit": 96,
	"Other": 433
 },
 {
	"communityBoard": "305",
	"count": 846,
	"Failure to Comply": 77,
	"Miscellaneous": 79,
	"Building Maintenance": 87,
	"Elevator Maintenance": 36,
	"Work Without Permit": 131,
	"Other": 436
 },
 {
	"communityBoard": "306",
	"count": 717,
	"Failure to Comply": 34,
	"Miscellaneous": 149,
	"Building Maintenance": 83,
	"Elevator Maintenance": 35,
	"Work Without Permit": 65,
	"Other": 351
 },
 {
	"communityBoard": "307",
	"count": 735,
	"Failure to Comply": 39,
	"Miscellaneous": 66,
	"Building Maintenance": 86,
	"Elevator Maintenance": 77,
	"Work Without Permit": 93,
	"Other": 374
 },
 {
	"communityBoard": "308",
	"count": 538,
	"Failure to Comply": 25,
	"Miscellaneous": 59,
	"Building Maintenance": 66,
	"Elevator Maintenance": 61,
	"Work Without Permit": 59,
	"Other": 268
 },
 {
	"communityBoard": "309",
	"count": 638,
	"Failure to Comply": 33,
	"Miscellaneous": 48,
	"Building Maintenance": 94,
	"Elevator Maintenance": 85,
	"Work Without Permit": 53,
	"Other": 325
 },
 {
	"communityBoard": "310",
	"count": 584,
	"Failure to Comply": 21,
	"Miscellaneous": 29,
	"Building Maintenance": 75,
	"Elevator Maintenance": 100,
	"Work Without Permit": 109,
	"Other": 250
 },
 {
	"communityBoard": "311",
	"count": 543,
	"Failure to Comply": 30,
	"Miscellaneous": 66,
	"Building Maintenance": 51,
	"Elevator Maintenance": 56,
	"Work Without Permit": 93,
	"Other": 247
 },
 {
	"communityBoard": "312",
	"count": 862,
	"Failure to Comply": 36,
	"Miscellaneous": 96,
	"Building Maintenance": 77,
	"Elevator Maintenance": 100,
	"Work Without Permit": 206,
	"Other": 347
 },
 {
	"communityBoard": "313",
	"count": 413,
	"Failure to Comply": 18,
	"Miscellaneous": 32,
	"Building Maintenance": 38,
	"Elevator Maintenance": 118,
	"Work Without Permit": 47,
	"Other": 160
 },
 {
	"communityBoard": "314",
	"count": 858,
	"Failure to Comply": 60,
	"Miscellaneous": 49,
	"Building Maintenance": 115,
	"Elevator Maintenance": 235,
	"Work Without Permit": 101,
	"Other": 298
 },
 {
	"communityBoard": "315",
	"count": 727,
	"Failure to Comply": 36,
	"Miscellaneous": 78,
	"Building Maintenance": 64,
	"Elevator Maintenance": 133,
	"Work Without Permit": 134,
	"Other": 282
 },
 {
	"communityBoard": "316",
	"count": 527,
	"Failure to Comply": 17,
	"Miscellaneous": 53,
	"Building Maintenance": 105,
	"Elevator Maintenance": 33,
	"Work Without Permit": 45,
	"Other": 274
 },
 {
	"communityBoard": "317",
	"count": 723,
	"Failure to Comply": 22,
	"Miscellaneous": 60,
	"Building Maintenance": 94,
	"Elevator Maintenance": 97,
	"Work Without Permit": 113,
	"Other": 337
 },
 {
	"communityBoard": "318",
	"count": 439,
	"Failure to Comply": 24,
	"Miscellaneous": 49,
	"Building Maintenance": 51,
	"Elevator Maintenance": 39,
	"Work Without Permit": 113,
	"Other": 163
 },
 {
	"communityBoard": "355",
	"count": 0,
	"Failure to Comply": 0,
	"Miscellaneous": 0,
	"Building Maintenance": 0,
	"Elevator Maintenance": 0,
	"Work Without Permit": 0,
	"Other": 0
 },
 {
	"communityBoard": "356",
	"count": 0,
	"Failure to Comply": 0,
	"Miscellaneous": 0,
	"Building Maintenance": 0,
	"Elevator Maintenance": 0,
	"Work Without Permit": 0,
	"Other": 0
 },
 {
	"communityBoard": "401",
	"count": 983,
	"Failure to Comply": 36,
	"Miscellaneous": 152,
	"Building Maintenance": 84,
	"Elevator Maintenance": 29,
	"Work Without Permit": 93,
	"Other": 589
 },
 {
	"communityBoard": "402",
	"count": 613,
	"Failure to Comply": 28,
	"Miscellaneous": 130,
	"Building Maintenance": 67,
	"Elevator Maintenance": 23,
	"Work Without Permit": 45,
	"Other": 320
 },
 {
	"communityBoard": "403",
	"count": 438,
	"Failure to Comply": 15,
	"Miscellaneous": 51,
	"Building Maintenance": 48,
	"Elevator Maintenance": 36,
	"Work Without Permit": 69,
	"Other": 219
 },
 {
	"communityBoard": "404",
	"count": 459,
	"Failure to Comply": 22,
	"Miscellaneous": 44,
	"Building Maintenance": 48,
	"Elevator Maintenance": 24,
	"Work Without Permit": 51,
	"Other": 270
 },
 {
	"communityBoard": "405",
	"count": 401,
	"Failure to Comply": 25,
	"Miscellaneous": 38,
	"Building Maintenance": 48,
	"Elevator Maintenance": 6,
	"Work Without Permit": 95,
	"Other": 189
 },
 {
	"communityBoard": "406",
	"count": 358,
	"Failure to Comply": 12,
	"Miscellaneous": 51,
	"Building Maintenance": 33,
	"Elevator Maintenance": 22,
	"Work Without Permit": 40,
	"Other": 200
 },
 {
	"communityBoard": "407",
	"count": 1095,
	"Failure to Comply": 21,
	"Miscellaneous": 156,
	"Building Maintenance": 70,
	"Elevator Maintenance": 52,
	"Work Without Permit": 171,
	"Other": 625
 },
 {
	"communityBoard": "408",
	"count": 456,
	"Failure to Comply": 22,
	"Miscellaneous": 53,
	"Building Maintenance": 47,
	"Elevator Maintenance": 30,
	"Work Without Permit": 74,
	"Other": 230
 },
 {
	"communityBoard": "409",
	"count": 470,
	"Failure to Comply": 17,
	"Miscellaneous": 56,
	"Building Maintenance": 41,
	"Elevator Maintenance": 20,
	"Work Without Permit": 104,
	"Other": 232
 },
 {
	"communityBoard": "410",
	"count": 498,
	"Failure to Comply": 39,
	"Miscellaneous": 55,
	"Building Maintenance": 57,
	"Elevator Maintenance": 3,
	"Work Without Permit": 133,
	"Other": 211
 },
 {
	"communityBoard": "411",
	"count": 379,
	"Failure to Comply": 8,
	"Miscellaneous": 53,
	"Building Maintenance": 35,
	"Elevator Maintenance": 3,
	"Work Without Permit": 53,
	"Other": 227
 },
 {
	"communityBoard": "412",
	"count": 965,
	"Failure to Comply": 58,
	"Miscellaneous": 80,
	"Building Maintenance": 119,
	"Elevator Maintenance": 76,
	"Work Without Permit": 166,
	"Other": 466
 },
 {
	"communityBoard": "413",
	"count": 401,
	"Failure to Comply": 8,
	"Miscellaneous": 30,
	"Building Maintenance": 50,
	"Elevator Maintenance": 6,
	"Work Without Permit": 108,
	"Other": 199
 },
 {
	"communityBoard": "414",
	"count": 309,
	"Failure to Comply": 19,
	"Miscellaneous": 18,
	"Building Maintenance": 56,
	"Elevator Maintenance": 33,
	"Work Without Permit": 49,
	"Other": 134
 },
 {
	"communityBoard": "480",
	"count": 0,
	"Failure to Comply": 0,
	"Miscellaneous": 0,
	"Building Maintenance": 0,
	"Elevator Maintenance": 0,
	"Work Without Permit": 0,
	"Other": 0
 },
 {
	"communityBoard": "481",
	"count": 0,
	"Failure to Comply": 0,
	"Miscellaneous": 0,
	"Building Maintenance": 0,
	"Elevator Maintenance": 0,
	"Work Without Permit": 0,
	"Other": 0
 },
 {
	"communityBoard": "482",
	"count": 0,
	"Failure to Comply": 0,
	"Miscellaneous": 0,
	"Building Maintenance": 0,
	"Elevator Maintenance": 0,
	"Work Without Permit": 0,
	"Other": 0
 },
 {
	"communityBoard": "483",
	"count": 0,
	"Failure to Comply": 0,
	"Miscellaneous": 0,
	"Building Maintenance": 0,
	"Elevator Maintenance": 0,
	"Work Without Permit": 0,
	"Other": 0
 },
 {
	"communityBoard": "484",
	"count": 0,
	"Failure to Comply": 0,
	"Miscellaneous": 0,
	"Building Maintenance": 0,
	"Elevator Maintenance": 0,
	"Work Without Permit": 0,
	"Other": 0
 },
 {
	"communityBoard": "501",
	"count": 521,
	"Failure to Comply": 27,
	"Miscellaneous": 35,
	"Building Maintenance": 71,
	"Elevator Maintenance": 33,
	"Work Without Permit": 114,
	"Other": 241
 },
 {
	"communityBoard": "502",
	"count": 326,
	"Failure to Comply": 11,
	"Miscellaneous": 31,
	"Building Maintenance": 50,
	"Elevator Maintenance": 3,
	"Work Without Permit": 87,
	"Other": 144
 },
 {
	"communityBoard": "503",
	"count": 278,
	"Failure to Comply": 26,
	"Miscellaneous": 37,
	"Building Maintenance": 18,
	"Elevator Maintenance": 0,
	"Work Without Permit": 67,
	"Other": 130
 },
 {
	"communityBoard": "595",
	"count": 0,
	"Failure to Comply": 0,
	"Miscellaneous": 0,
	"Building Maintenance": 0,
	"Elevator Maintenance": 0,
	"Work Without Permit": 0,
	"Other": 0
 }
]