[
 {
	"count": 57,
	"communityBoard": "101",
	"NB": 11,
	"A1": 46
 },
 {
	"count": 142,
	"communityBoard": "102",
	"NB": 53,
	"A1": 89
 },
 {
	"count": 106,
	"communityBoard": "103",
	"NB": 55,
	"A1": 51
 },
 {
	"count": 164,
	"communityBoard": "104",
	"NB": 117,
	"A1": 47
 },
 {
	"count": 102,
	"communityBoard": "105",
	"NB": 54,
	"A1": 48
 },
 {
	"count": 38,
	"communityBoard": "106",
	"NB": 29,
	"A1": 9
 },
 {
	"count": 47,
	"communityBoard": "107",
	"NB": 15,
	"A1": 32
 },
 {
	"count": 141,
	"communityBoard": "108",
	"NB": 91,
	"A1": 50
 },
 {
	"count": 38,
	"communityBoard": "109",
	"NB": 27,
	"A1": 11
 },
 {
	"count": 84,
	"communityBoard": "110",
	"NB": 60,
	"A1": 24
 },
 {
	"count": 78,
	"communityBoard": "111",
	"NB": 70,
	"A1": 8
 },
 {
	"count": 78,
	"communityBoard": "112",
	"NB": 66,
	"A1": 12
 },
 {
	"count": 10,
	"communityBoard": "164",
	"NB": 10,
	"A1": 0
 },
 {
	"count": 130,
	"communityBoard": "201",
	"NB": 126,
	"A1": 4
 },
 {
	"count": 36,
	"communityBoard": "202",
	"NB": 31,
	"A1": 5
 },
 {
	"count": 85,
	"communityBoard": "203",
	"NB": 80,
	"A1": 5
 },
 {
	"count": 94,
	"communityBoard": "204",
	"NB": 89,
	"A1": 5
 },
 {
	"count": 153,
	"communityBoard": "205",
	"NB": 148,
	"A1": 5
 },
 {
	"count": 95,
	"communityBoard": "206",
	"NB": 82,
	"A1": 13
 },
 {
	"count": 96,
	"communityBoard": "207",
	"NB": 87,
	"A1": 9
 },
 {
	"count": 81,
	"communityBoard": "208",
	"NB": 68,
	"A1": 13
 },
 {
	"count": 72,
	"communityBoard": "209",
	"NB": 62,
	"A1": 10
 },
 {
	"count": 73,
	"communityBoard": "210",
	"NB": 65,
	"A1": 8
 },
 {
	"count": 78,
	"communityBoard": "211",
	"NB": 66,
	"A1": 12
 },
 {
	"count": 130,
	"communityBoard": "212",
	"NB": 112,
	"A1": 18
 },
 {
	"count": 2,
	"communityBoard": "226",
	"NB": 1,
	"A1": 1
 },
 {
	"count": 0,
	"communityBoard": "227",
	"NB": 0,
	"A1": 0
 },
 {
	"count": 7,
	"communityBoard": "228",
	"NB": 7,
	"A1": 0
 },
 {
	"count": 543,
	"communityBoard": "301",
	"NB": 478,
	"A1": 65
 },
 {
	"count": 230,
	"communityBoard": "302",
	"NB": 185,
	"A1": 45
 },
 {
	"count": 293,
	"communityBoard": "303",
	"NB": 251,
	"A1": 42
 },
 {
	"count": 139,
	"communityBoard": "304",
	"NB": 115,
	"A1": 24
 },
 {
	"count": 239,
	"communityBoard": "305",
	"NB": 223,
	"A1": 16
 },
 {
	"count": 291,
	"communityBoard": "306",
	"NB": 247,
	"A1": 44
 },
 {
	"count": 137,
	"communityBoard": "307",
	"NB": 105,
	"A1": 32
 },
 {
	"count": 138,
	"communityBoard": "308",
	"NB": 109,
	"A1": 29
 },
 {
	"count": 130,
	"communityBoard": "309",
	"NB": 118,
	"A1": 12
 },
 {
	"count": 68,
	"communityBoard": "310",
	"NB": 53,
	"A1": 15
 },
 {
	"count": 72,
	"communityBoard": "311",
	"NB": 57,
	"A1": 15
 },
 {
	"count": 334,
	"communityBoard": "312",
	"NB": 298,
	"A1": 36
 },
 {
	"count": 101,
	"communityBoard": "313",
	"NB": 90,
	"A1": 11
 },
 {
	"count": 95,
	"communityBoard": "314",
	"NB": 75,
	"A1": 20
 },
 {
	"count": 188,
	"communityBoard": "315",
	"NB": 149,
	"A1": 39
 },
 {
	"count": 127,
	"communityBoard": "316",
	"NB": 118,
	"A1": 9
 },
 {
	"count": 136,
	"communityBoard": "317",
	"NB": 122,
	"A1": 14
 },
 {
	"count": 50,
	"communityBoard": "318",
	"NB": 32,
	"A1": 18
 },
 {
	"count": 0,
	"communityBoard": "355",
	"NB": 0,
	"A1": 0
 },
 {
	"count": 0,
	"communityBoard": "356",
	"NB": 0,
	"A1": 0
 },
 {
	"count": 259,
	"communityBoard": "401",
	"NB": 222,
	"A1": 37
 },
 {
	"count": 179,
	"communityBoard": "402",
	"NB": 167,
	"A1": 12
 },
 {
	"count": 71,
	"communityBoard": "403",
	"NB": 56,
	"A1": 15
 },
 {
	"count": 90,
	"communityBoard": "404",
	"NB": 84,
	"A1": 6
 },
 {
	"count": 104,
	"communityBoard": "405",
	"NB": 85,
	"A1": 19
 },
 {
	"count": 78,
	"communityBoard": "406",
	"NB": 66,
	"A1": 12
 },
 {
	"count": 486,
	"communityBoard": "407",
	"NB": 456,
	"A1": 30
 },
 {
	"count": 130,
	"communityBoard": "408",
	"NB": 102,
	"A1": 28
 },
 {
	"count": 54,
	"communityBoard": "409",
	"NB": 39,
	"A1": 15
 },
 {
	"count": 79,
	"communityBoard": "410",
	"NB": 61,
	"A1": 18
 },
 {
	"count": 253,
	"communityBoard": "411",
	"NB": 234,
	"A1": 19
 },
 {
	"count": 206,
	"communityBoard": "412",
	"NB": 182,
	"A1": 24
 },
 {
	"count": 123,
	"communityBoard": "413",
	"NB": 109,
	"A1": 14
 },
 {
	"count": 241,
	"communityBoard": "414",
	"NB": 224,
	"A1": 17
 },
 {
	"count": 0,
	"communityBoard": "480",
	"NB": 0,
	"A1": 0
 },
 {
	"count": 1,
	"communityBoard": "481",
	"NB": 0,
	"A1": 1
 },
 {
	"count": 0,
	"communityBoard": "482",
	"NB": 0,
	"A1": 0
 },
 {
	"count": 2,
	"communityBoard": "483",
	"NB": 2,
	"A1": 0
 },
 {
	"count": 0,
	"communityBoard": "484",
	"NB": 0,
	"A1": 0
 },
 {
	"count": 378,
	"communityBoard": "501",
	"NB": 357,
	"A1": 21
 },
 {
	"count": 384,
	"communityBoard": "502",
	"NB": 361,
	"A1": 23
 },
 {
	"count": 705,
	"communityBoard": "503",
	"NB": 689,
	"A1": 16
 },
 {
	"count": 0,
	"communityBoard": "595",
	"NB": 0,
	"A1": 0
 }
]