[
 {
	"values": 
	[
		{		
		"x": "Bronx",
		"y": 210
		},
		 {		
		"x": "Brooklyn",
		"y": 948
		},
		 {		
		"x": "Manhattan",
		"y": 737
		},
		 {		
		"x": "Queens",
		"y": 599
		},
		 {		
		"x": "Staten Island",
		"y": 120
		} 
	],
	"key": "A1"
 },
 {
	"values": 
	[
		{		
		"x": "Bronx",
		"y": 739
		}
,
		 {		
		"x": "Brooklyn",
		"y": 1740
		},
		 {		
		"x": "Manhattan",
		"y": 426
		},
		 {		
		"x": "Queens",
		"y": 1488
		},
		 {		
		"x": "Staten Island",
		"y": 1120
		}
	],
	"key": "NB"
 }
]