[
 {
	"values": 
	[
		{		
		"x": "Bronx",
		"y": 961
		},
		 {		
		"x": "Brooklyn",
		"y": 1819
		},
		 {		
		"x": "Manhattan",
		"y": 1568
		},
		 {		
		"x": "Queens",
		"y": 823
		},
		 {		
		"x": "Staten Island",
		"y": 210
		} 
	],
	"key": "Building Maintenance"
 },
 {
	"values": 
	[
		{		
		"x": "Bronx",
		"y": 833
		}
,
		 {		
		"x": "Brooklyn",
		"y": 1531
		},
		 {		
		"x": "Manhattan",
		"y": 851
		},
		 {		
		"x": "Queens",
		"y": 373
		},
		 {		
		"x": "Staten Island",
		"y": 51
		} 
	],
	"key": "Elevator Maintenance"
 },
 {
	"values": 
	[
		{		
		"x": "Bronx",
		"y": 302
		}
,
		 {		
		"x": "Brooklyn",
		"y": 439
		},
		 {		
		"x": "Manhattan",
		"y": 293
		},
		 {		
		"x": "Queens",
		"y": 219
		},
		 {		
		"x": "Staten Island",
		"y": 53
		} 
	],
	"key": "Failure to Comply"
 },
 {
	"values": 
	[
		{		
		"x": "Bronx",
		"y": 914
		}
,
		 {		
		"x": "Brooklyn",
		"y": 2000
		},
		 {		
		"x": "Manhattan",
		"y": 1454
		},
		 {		
		"x": "Queens",
		"y": 1255
		},
		 {		
		"x": "Staten Island",
		"y": 143
		} 
	],
	"key": "Miscellaneous"
 },
 {
	"values": 
	[
		{		
		"x": "Bronx",
		"y": 4077
		}
,
		 {		
		"x": "Brooklyn",
		"y": 7733
		},
		 {		
		"x": "Manhattan",
		"y": 5986
		},
		 {		
		"x": "Queens",
		"y": 4735
		},
		 {		
		"x": "Staten Island",
		"y": 631
		} 
	],
	"key": "Other"
 },
 {
	"values": 
	[
		{		
		"x": "Bronx",
		"y": 579
		}
,
		 {		
		"x": "Brooklyn",
		"y": 1434
		},
		 {		
		"x": "Manhattan",
		"y": 721
		},
		 {		
		"x": "Queens",
		"y": 931
		},
		 {		
		"x": "Staten Island",
		"y": 174
		}
	],
	"key": "Work Without Permit"
 }
]