[
 {
	"communityBoard": "101",
	"averageAge": 247.14935548843877
 },
 {
	"communityBoard": "102",
	"averageAge": 177.02655377700515
 },
 {
	"communityBoard": "103",
	"averageAge": 215.18965031550482
 },
 {
	"communityBoard": "104",
	"averageAge": 217.31696585323033
 },
 {
	"communityBoard": "105",
	"averageAge": 186.17125208545508
 },
 {
	"communityBoard": "106",
	"averageAge": 176.55630245262168
 },
 {
	"communityBoard": "107",
	"averageAge": 234.53719608546183
 },
 {
	"communityBoard": "108",
	"averageAge": 177.88361104329428
 },
 {
	"communityBoard": "109",
	"averageAge": 228.6831716125757
 },
 {
	"communityBoard": "110",
	"averageAge": 182.9409960750419
 },
 {
	"communityBoard": "111",
	"averageAge": 167.94183461600488
 },
 {
	"communityBoard": "112",
	"averageAge": 185.8508530254512
 },
 {
	"communityBoard": "164",
	"averageAge": 264.5
 },
 {
	"communityBoard": "201",
	"averageAge": 231.30838636172714
 },
 {
	"communityBoard": "202",
	"averageAge": 176.83333333333334
 },
 {
	"communityBoard": "203",
	"averageAge": 219.38015581471052
 },
 {
	"communityBoard": "204",
	"averageAge": 275.56483054045896
 },
 {
	"communityBoard": "205",
	"averageAge": 178.3968629525378
 },
 {
	"communityBoard": "206",
	"averageAge": 176.3691432407924
 },
 {
	"communityBoard": "207",
	"averageAge": 202.9670889166337
 },
 {
	"communityBoard": "208",
	"averageAge": 220.86752347333714
 },
 {
	"communityBoard": "209",
	"averageAge": 204.95726495726495
 },
 {
	"communityBoard": "210",
	"averageAge": 213.38214329310827
 },
 {
	"communityBoard": "211",
	"averageAge": 175.84547905072773
 },
 {
	"communityBoard": "212",
	"averageAge": 181.6144578313253
 },
 {
	"communityBoard": "226",
	"averageAge": 0.0
 },
 {
	"communityBoard": "227",
	"averageAge": 87.0
 },
 {
	"communityBoard": "228",
	"averageAge": 0.0
 },
 {
	"communityBoard": "301",
	"averageAge": 216.37999971034162
 },
 {
	"communityBoard": "302",
	"averageAge": 189.98202922655187
 },
 {
	"communityBoard": "303",
	"averageAge": 200.4915700865186
 },
 {
	"communityBoard": "304",
	"averageAge": 193.03565116550612
 },
 {
	"communityBoard": "305",
	"averageAge": 234.98174598233012
 },
 {
	"communityBoard": "306",
	"averageAge": 156.25871697191923
 },
 {
	"communityBoard": "307",
	"averageAge": 193.90686558965427
 },
 {
	"communityBoard": "308",
	"averageAge": 182.3604542125355
 },
 {
	"communityBoard": "309",
	"averageAge": 238.62157517336726
 },
 {
	"communityBoard": "310",
	"averageAge": 167.43771449497768
 },
 {
	"communityBoard": "311",
	"averageAge": 165.62325553006903
 },
 {
	"communityBoard": "312",
	"averageAge": 148.1037037037037
 },
 {
	"communityBoard": "313",
	"averageAge": 196.7020498422476
 },
 {
	"communityBoard": "314",
	"averageAge": 203.87555609809027
 },
 {
	"communityBoard": "315",
	"averageAge": 164.79826067496037
 },
 {
	"communityBoard": "316",
	"averageAge": 221.67458624588815
 },
 {
	"communityBoard": "317",
	"averageAge": 151.94117647058823
 },
 {
	"communityBoard": "318",
	"averageAge": 292.91058852251837
 },
 {
	"communityBoard": "355",
	"averageAge": 0.0
 },
 {
	"communityBoard": "356",
	"averageAge": 0.0
 },
 {
	"communityBoard": "401",
	"averageAge": 180.44778988486843
 },
 {
	"communityBoard": "402",
	"averageAge": 186.58707260504002
 },
 {
	"communityBoard": "403",
	"averageAge": 198.5904773530506
 },
 {
	"communityBoard": "404",
	"averageAge": 160.40740740740742
 },
 {
	"communityBoard": "405",
	"averageAge": 156.69826076341712
 },
 {
	"communityBoard": "406",
	"averageAge": 190.9877971067267
 },
 {
	"communityBoard": "407",
	"averageAge": 215.53561568586792
 },
 {
	"communityBoard": "408",
	"averageAge": 242.60290971235796
 },
 {
	"communityBoard": "409",
	"averageAge": 218.49106289478058
 },
 {
	"communityBoard": "410",
	"averageAge": 194.37793179216055
 },
 {
	"communityBoard": "411",
	"averageAge": 182.18316007915297
 },
 {
	"communityBoard": "412",
	"averageAge": 215.82148121021413
 },
 {
	"communityBoard": "413",
	"averageAge": 146.10344827586206
 },
 {
	"communityBoard": "414",
	"averageAge": 210.6206896551724
 },
 {
	"communityBoard": "480",
	"averageAge": 0.0
 },
 {
	"communityBoard": "481",
	"averageAge": 153.0
 },
 {
	"communityBoard": "482",
	"averageAge": 0.0
 },
 {
	"communityBoard": "483",
	"averageAge": 0.0
 },
 {
	"communityBoard": "484",
	"averageAge": 0.0
 },
 {
	"communityBoard": "501",
	"averageAge": 269.94098500736425
 },
 {
	"communityBoard": "502",
	"averageAge": 317.1549987792969
 },
 {
	"communityBoard": "503",
	"averageAge": 126.3076923076923
 },
 {
	"communityBoard": "595",
	"averageAge": 0.0
 }
]