[{"count":278,"communityBoard":"101","Construction":127,"LL 11":151,"Avg Days":315.6087951660156,"Total Feet":60419.0},{"count":454,"communityBoard":"102","Construction":311,"LL 11":143,"Avg Days":258.5898742675781,"Total Feet":62502.2109375},{"count":256,"communityBoard":"103","Construction":188,"LL 11":68,"Avg Days":245.39883422851562,"Total Feet":56802.0},{"count":398,"communityBoard":"104","Construction":255,"LL 11":143,"Avg Days":249.47677612304688,"Total Feet":78417.0},{"count":649,"communityBoard":"105","Construction":235,"LL 11":414,"Avg Days":250.9179229736328,"Total Feet":118737.5},{"count":296,"communityBoard":"106","Construction":140,"LL 11":156,"Avg Days":257.32647705078125,"Total Feet":61432.0},{"count":499,"communityBoard":"107","Construction":232,"LL 11":267,"Avg Days":293.2392272949219,"Total Feet":91197.0},{"count":575,"communityBoard":"108","Construction":308,"LL 11":267,"Avg Days":245.32095336914062,"Total Feet":92844.5},{"count":233,"communityBoard":"109","Construction":121,"LL 11":112,"Avg Days":269.153564453125,"Total Feet":51663.0},{"count":226,"communityBoard":"110","Construction":150,"LL 11":76,"Avg Days":247.52430725097656,"Total Feet":43388.5},{"count":200,"communityBoard":"111","Construction":125,"LL 11":75,"Avg Days":263.2364807128906,"Total Feet":49283.0},{"count":221,"communityBoard":"112","Construction":131,"LL 11":90,"Avg Days":200.07345581054688,"Total Feet":48237.0},{"count":1,"communityBoard":"164","Construction":0,"LL 11":1,"Avg Days":209.0,"Total Feet":370.0},{"count":163,"communityBoard":"201","Construction":117,"LL 11":46,"Avg Days":286.192626953125,"Total Feet":46652.0},{"count":52,"communityBoard":"202","Construction":45,"LL 11":7,"Avg Days":217.5814208984375,"Total Feet":9928.0},{"count":129,"communityBoard":"203","Construction":82,"LL 11":47,"Avg Days":261.5927734375,"Total Feet":35337.0},{"count":154,"communityBoard":"204","Construction":95,"LL 11":59,"Avg Days":297.93072509765625,"Total Feet":41726.0},{"count":119,"communityBoard":"205","Construction":85,"LL 11":34,"Avg Days":241.47488403320312,"Total Feet":21617.0},{"count":89,"communityBoard":"206","Construction":73,"LL 11":16,"Avg Days":225.61767578125,"Total Feet":17240.0},{"count":94,"communityBoard":"207","Construction":73,"LL 11":21,"Avg Days":269.1600036621094,"Total Feet":15859.0},{"count":112,"communityBoard":"208","Construction":42,"LL 11":70,"Avg Days":225.00210571289062,"Total Feet":35275.0},{"count":110,"communityBoard":"209","Construction":40,"LL 11":70,"Avg Days":242.77967834472656,"Total Feet":54932.0},{"count":41,"communityBoard":"210","Construction":33,"LL 11":8,"Avg Days":226.15077209472656,"Total Feet":37958.0},{"count":62,"communityBoard":"211","Construction":47,"LL 11":15,"Avg Days":348.9393615722656,"Total Feet":17870.0},{"count":70,"communityBoard":"212","Construction":48,"LL 11":22,"Avg Days":197.4783935546875,"Total Feet":15961.0},{"count":0,"communityBoard":"226","Construction":0,"LL 11":0,"Avg Days":0.0,"Total Feet":0.0},{"count":0,"communityBoard":"227","Construction":0,"LL 11":0,"Avg Days":0.0,"Total Feet":0.0},{"count":0,"communityBoard":"228","Construction":0,"LL 11":0,"Avg Days":0.0,"Total Feet":0.0},{"count":360,"communityBoard":"301","Construction":323,"LL 11":37,"Avg Days":243.9251708984375,"Total Feet":60446.0},{"count":323,"communityBoard":"302","Construction":242,"LL 11":81,"Avg Days":271.5195617675781,"Total Feet":67477.0},{"count":277,"communityBoard":"303","Construction":258,"LL 11":19,"Avg Days":243.04624938964844,"Total Feet":31119.0},{"count":125,"communityBoard":"304","Construction":122,"LL 11":3,"Avg Days":189.6084442138672,"Total Feet":13604.0},{"count":111,"communityBoard":"305","Construction":99,"LL 11":12,"Avg Days":219.4563446044922,"Total Feet":18829.0},{"count":227,"communityBoard":"306","Construction":207,"LL 11":20,"Avg Days":218.7754364013672,"Total Feet":42977.0},{"count":117,"communityBoard":"307","Construction":114,"LL 11":3,"Avg Days":225.10797119140625,"Total Feet":14886.0},{"count":107,"communityBoard":"308","Construction":95,"LL 11":12,"Avg Days":269.2939147949219,"Total Feet":14185.0},{"count":81,"communityBoard":"309","Construction":72,"LL 11":9,"Avg Days":245.36190795898438,"Total Feet":17902.0},{"count":75,"communityBoard":"310","Construction":55,"LL 11":20,"Avg Days":255.05038452148438,"Total Feet":13316.0},{"count":57,"communityBoard":"311","Construction":52,"LL 11":5,"Avg Days":183.86199951171875,"Total Feet":10913.0},{"count":141,"communityBoard":"312","Construction":137,"LL 11":4,"Avg Days":179.52000427246094,"Total Feet":22642.0},{"count":86,"communityBoard":"313","Construction":44,"LL 11":42,"Avg Days":239.69677734375,"Total Feet":39021.0},{"count":109,"communityBoard":"314","Construction":90,"LL 11":19,"Avg Days":226.8271484375,"Total Feet":18295.0},{"count":62,"communityBoard":"315","Construction":55,"LL 11":7,"Avg Days":290.70220947265625,"Total Feet":10113.0},{"count":123,"communityBoard":"316","Construction":73,"LL 11":50,"Avg Days":230.9043731689453,"Total Feet":22314.0},{"count":100,"communityBoard":"317","Construction":97,"LL 11":3,"Avg Days":185.8182830810547,"Total Feet":14787.0},{"count":65,"communityBoard":"318","Construction":27,"LL 11":38,"Avg Days":321.64178466796875,"Total Feet":25095.0},{"count":0,"communityBoard":"355","Construction":0,"LL 11":0,"Avg Days":0.0,"Total Feet":0.0},{"count":0,"communityBoard":"356","Construction":0,"LL 11":0,"Avg Days":0.0,"Total Feet":0.0},{"count":222,"communityBoard":"401","Construction":178,"LL 11":44,"Avg Days":239.61463928222656,"Total Feet":36882.0},{"count":144,"communityBoard":"402","Construction":122,"LL 11":22,"Avg Days":339.47894287109375,"Total Feet":27161.0},{"count":70,"communityBoard":"403","Construction":54,"LL 11":16,"Avg Days":203.9246826171875,"Total Feet":16182.0},{"count":65,"communityBoard":"404","Construction":42,"LL 11":23,"Avg Days":216.207763671875,"Total Feet":12414.0},{"count":44,"communityBoard":"405","Construction":42,"LL 11":2,"Avg Days":251.91363525390625,"Total Feet":6926.0},{"count":97,"communityBoard":"406","Construction":45,"LL 11":52,"Avg Days":193.82679748535156,"Total Feet":26529.0},{"count":106,"communityBoard":"407","Construction":70,"LL 11":36,"Avg Days":238.10169982910156,"Total Feet":25955.0},{"count":65,"communityBoard":"408","Construction":49,"LL 11":16,"Avg Days":211.4501495361328,"Total Feet":13454.0},{"count":42,"communityBoard":"409","Construction":26,"LL 11":16,"Avg Days":193.45166015625,"Total Feet":12203.0},{"count":23,"communityBoard":"410","Construction":21,"LL 11":2,"Avg Days":192.16444396972656,"Total Feet":6231.0},{"count":21,"communityBoard":"411","Construction":20,"LL 11":1,"Avg Days":206.95809936523438,"Total Feet":4988.0},{"count":93,"communityBoard":"412","Construction":63,"LL 11":30,"Avg Days":272.8208312988281,"Total Feet":24356.0},{"count":13,"communityBoard":"413","Construction":10,"LL 11":3,"Avg Days":146.25999450683594,"Total Feet":2353.0},{"count":54,"communityBoard":"414","Construction":35,"LL 11":19,"Avg Days":258.08135986328125,"Total Feet":19078.0},{"count":0,"communityBoard":"480","Construction":0,"LL 11":0,"Avg Days":0.0,"Total Feet":0.0},{"count":0,"communityBoard":"481","Construction":0,"LL 11":0,"Avg Days":0.0,"Total Feet":0.0},{"count":0,"communityBoard":"482","Construction":0,"LL 11":0,"Avg Days":0.0,"Total Feet":0.0},{"count":0,"communityBoard":"483","Construction":0,"LL 11":0,"Avg Days":0.0,"Total Feet":0.0},{"count":0,"communityBoard":"484","Construction":0,"LL 11":0,"Avg Days":0.0,"Total Feet":0.0},{"count":42,"communityBoard":"501","Construction":35,"LL 11":7,"Avg Days":301.548828125,"Total Feet":6264.0},{"count":19,"communityBoard":"502","Construction":13,"LL 11":6,"Avg Days":225.0704803466797,"Total Feet":6008.0},{"count":3,"communityBoard":"503","Construction":3,"LL 11":0,"Avg Days":405.25335693359375,"Total Feet":1059.0},{"count":0,"communityBoard":"595","Construction":0,"LL 11":0,"Avg Days":0.0,"Total Feet":0.0}]