[{"communityBoard":"101","count":884,"Building Maintenance":40,"Elevator Maintenance":122,"Failure to Comply":74,"Miscellaneous":140,"Work Without Permit":35,"Other":473},{"communityBoard":"102","count":1613,"Building Maintenance":110,"Elevator Maintenance":62,"Failure to Comply":192,"Miscellaneous":243,"Work Without Permit":124,"Other":882},{"communityBoard":"103","count":2030,"Building Maintenance":214,"Elevator Maintenance":65,"Failure to Comply":262,"Miscellaneous":292,"Work Without Permit":147,"Other":1050},{"communityBoard":"104","count":1736,"Building Maintenance":149,"Elevator Maintenance":100,"Failure to Comply":198,"Miscellaneous":321,"Work Without Permit":91,"Other":877},{"communityBoard":"105","count":2063,"Building Maintenance":76,"Elevator Maintenance":300,"Failure to Comply":205,"Miscellaneous":340,"Work Without Permit":90,"Other":1052},{"communityBoard":"106","count":1221,"Building Maintenance":109,"Elevator Maintenance":136,"Failure to Comply":134,"Miscellaneous":179,"Work Without Permit":75,"Other":588},{"communityBoard":"107","count":1442,"Building Maintenance":132,"Elevator Maintenance":153,"Failure to Comply":145,"Miscellaneous":190,"Work Without Permit":108,"Other":714},{"communityBoard":"108","count":1551,"Building Maintenance":91,"Elevator Maintenance":111,"Failure to Comply":138,"Miscellaneous":252,"Work Without Permit":108,"Other":851},{"communityBoard":"109","count":1043,"Building Maintenance":72,"Elevator Maintenance":158,"Failure to Comply":116,"Miscellaneous":118,"Work Without Permit":70,"Other":509},{"communityBoard":"110","count":1394,"Building Maintenance":83,"Elevator Maintenance":238,"Failure to Comply":239,"Miscellaneous":131,"Work Without Permit":62,"Other":641},{"communityBoard":"111","count":996,"Building Maintenance":87,"Elevator Maintenance":105,"Failure to Comply":140,"Miscellaneous":75,"Work Without Permit":59,"Other":530},{"communityBoard":"112","count":1622,"Building Maintenance":122,"Elevator Maintenance":261,"Failure to Comply":268,"Miscellaneous":137,"Work Without Permit":152,"Other":682},{"communityBoard":"164","count":1,"Building Maintenance":0,"Elevator Maintenance":0,"Failure to Comply":0,"Miscellaneous":0,"Work Without Permit":0,"Other":1},{"communityBoard":"201","count":792,"Building Maintenance":45,"Elevator Maintenance":125,"Failure to Comply":103,"Miscellaneous":114,"Work Without Permit":30,"Other":375},{"communityBoard":"202","count":619,"Building Maintenance":67,"Elevator Maintenance":100,"Failure to Comply":113,"Miscellaneous":57,"Work Without Permit":35,"Other":247},{"communityBoard":"203","count":976,"Building Maintenance":61,"Elevator Maintenance":78,"Failure to Comply":264,"Miscellaneous":64,"Work Without Permit":64,"Other":445},{"communityBoard":"204","count":1288,"Building Maintenance":136,"Elevator Maintenance":229,"Failure to Comply":246,"Miscellaneous":67,"Work Without Permit":85,"Other":525},{"communityBoard":"205","count":1104,"Building Maintenance":89,"Elevator Maintenance":213,"Failure to Comply":177,"Miscellaneous":99,"Work Without Permit":78,"Other":448},{"communityBoard":"206","count":859,"Building Maintenance":61,"Elevator Maintenance":117,"Failure to Comply":183,"Miscellaneous":79,"Work Without Permit":59,"Other":360},{"communityBoard":"207","count":1129,"Building Maintenance":84,"Elevator Maintenance":221,"Failure to Comply":223,"Miscellaneous":66,"Work Without Permit":87,"Other":448},{"communityBoard":"208","count":649,"Building Maintenance":46,"Elevator Maintenance":96,"Failure to Comply":103,"Miscellaneous":73,"Work Without Permit":48,"Other":283},{"communityBoard":"209","count":1129,"Building Maintenance":67,"Elevator Maintenance":131,"Failure to Comply":340,"Miscellaneous":52,"Work Without Permit":125,"Other":414},{"communityBoard":"210","count":698,"Building Maintenance":45,"Elevator Maintenance":30,"Failure to Comply":210,"Miscellaneous":39,"Work Without Permit":92,"Other":282},{"communityBoard":"211","count":861,"Building Maintenance":49,"Elevator Maintenance":88,"Failure to Comply":273,"Miscellaneous":40,"Work Without Permit":92,"Other":319},{"communityBoard":"212","count":1370,"Building Maintenance":115,"Elevator Maintenance":63,"Failure to Comply":456,"Miscellaneous":67,"Work Without Permit":158,"Other":511},{"communityBoard":"226","count":1,"Building Maintenance":0,"Elevator Maintenance":0,"Failure to Comply":0,"Miscellaneous":0,"Work Without Permit":0,"Other":1},{"communityBoard":"227","count":0,"Building Maintenance":0,"Elevator Maintenance":0,"Failure to Comply":0,"Miscellaneous":0,"Work Without Permit":0,"Other":0},{"communityBoard":"228","count":1,"Building Maintenance":0,"Elevator Maintenance":0,"Failure to Comply":0,"Miscellaneous":0,"Work Without Permit":1,"Other":0},{"communityBoard":"301","count":3048,"Building Maintenance":163,"Elevator Maintenance":152,"Failure to Comply":289,"Miscellaneous":630,"Work Without Permit":202,"Other":1612},{"communityBoard":"302","count":1602,"Building Maintenance":123,"Elevator Maintenance":79,"Failure to Comply":189,"Miscellaneous":249,"Work Without Permit":104,"Other":858},{"communityBoard":"303","count":2932,"Building Maintenance":170,"Elevator Maintenance":54,"Failure to Comply":566,"Miscellaneous":519,"Work Without Permit":151,"Other":1472},{"communityBoard":"304","count":1875,"Building Maintenance":121,"Elevator Maintenance":33,"Failure to Comply":326,"Miscellaneous":303,"Work Without Permit":160,"Other":932},{"communityBoard":"305","count":2057,"Building Maintenance":163,"Elevator Maintenance":83,"Failure to Comply":766,"Miscellaneous":133,"Work Without Permit":186,"Other":726},{"communityBoard":"306","count":1239,"Building Maintenance":97,"Elevator Maintenance":27,"Failure to Comply":144,"Miscellaneous":233,"Work Without Permit":82,"Other":656},{"communityBoard":"307","count":1459,"Building Maintenance":94,"Elevator Maintenance":53,"Failure to Comply":234,"Miscellaneous":239,"Work Without Permit":133,"Other":706},{"communityBoard":"308","count":1256,"Building Maintenance":74,"Elevator Maintenance":87,"Failure to Comply":234,"Miscellaneous":186,"Work Without Permit":74,"Other":601},{"communityBoard":"309","count":975,"Building Maintenance":58,"Elevator Maintenance":142,"Failure to Comply":117,"Miscellaneous":126,"Work Without Permit":59,"Other":473},{"communityBoard":"310","count":919,"Building Maintenance":45,"Elevator Maintenance":106,"Failure to Comply":147,"Miscellaneous":106,"Work Without Permit":127,"Other":388},{"communityBoard":"311","count":1155,"Building Maintenance":127,"Elevator Maintenance":83,"Failure to Comply":141,"Miscellaneous":176,"Work Without Permit":117,"Other":511},{"communityBoard":"312","count":1716,"Building Maintenance":90,"Elevator Maintenance":77,"Failure to Comply":226,"Miscellaneous":328,"Work Without Permit":138,"Other":857},{"communityBoard":"313","count":748,"Building Maintenance":47,"Elevator Maintenance":94,"Failure to Comply":95,"Miscellaneous":111,"Work Without Permit":74,"Other":327},{"communityBoard":"314","count":1205,"Building Maintenance":70,"Elevator Maintenance":156,"Failure to Comply":234,"Miscellaneous":128,"Work Without Permit":127,"Other":490},{"communityBoard":"315","count":1330,"Building Maintenance":103,"Elevator Maintenance":138,"Failure to Comply":168,"Miscellaneous":203,"Work Without Permit":159,"Other":559},{"communityBoard":"316","count":991,"Building Maintenance":77,"Elevator Maintenance":26,"Failure to Comply":328,"Miscellaneous":83,"Work Without Permit":66,"Other":411},{"communityBoard":"317","count":1472,"Building Maintenance":117,"Elevator Maintenance":106,"Failure to Comply":350,"Miscellaneous":164,"Work Without Permit":108,"Other":627},{"communityBoard":"318","count":1030,"Building Maintenance":81,"Elevator Maintenance":67,"Failure to Comply":221,"Miscellaneous":99,"Work Without Permit":162,"Other":400},{"communityBoard":"355","count":1,"Building Maintenance":0,"Elevator Maintenance":1,"Failure to Comply":0,"Miscellaneous":0,"Work Without Permit":0,"Other":0},{"communityBoard":"356","count":0,"Building Maintenance":0,"Elevator Maintenance":0,"Failure to Comply":0,"Miscellaneous":0,"Work Without Permit":0,"Other":0},{"communityBoard":"401","count":2120,"Building Maintenance":82,"Elevator Maintenance":79,"Failure to Comply":275,"Miscellaneous":419,"Work Without Permit":157,"Other":1108},{"communityBoard":"402","count":1290,"Building Maintenance":67,"Elevator Maintenance":80,"Failure to Comply":166,"Miscellaneous":271,"Work Without Permit":102,"Other":604},{"communityBoard":"403","count":1072,"Building Maintenance":89,"Elevator Maintenance":52,"Failure to Comply":222,"Miscellaneous":164,"Work Without Permit":100,"Other":445},{"communityBoard":"404","count":1138,"Building Maintenance":57,"Elevator Maintenance":69,"Failure to Comply":229,"Miscellaneous":168,"Work Without Permit":107,"Other":508},{"communityBoard":"405","count":1076,"Building Maintenance":91,"Elevator Maintenance":5,"Failure to Comply":204,"Miscellaneous":148,"Work Without Permit":181,"Other":447},{"communityBoard":"406","count":624,"Building Maintenance":32,"Elevator Maintenance":97,"Failure to Comply":39,"Miscellaneous":84,"Work Without Permit":57,"Other":315},{"communityBoard":"407","count":2162,"Building Maintenance":104,"Elevator Maintenance":95,"Failure to Comply":350,"Miscellaneous":333,"Work Without Permit":237,"Other":1043},{"communityBoard":"408","count":1039,"Building Maintenance":81,"Elevator Maintenance":35,"Failure to Comply":205,"Miscellaneous":123,"Work Without Permit":104,"Other":491},{"communityBoard":"409","count":1365,"Building Maintenance":108,"Elevator Maintenance":22,"Failure to Comply":426,"Miscellaneous":173,"Work Without Permit":177,"Other":459},{"communityBoard":"410","count":1115,"Building Maintenance":93,"Elevator Maintenance":5,"Failure to Comply":390,"Miscellaneous":96,"Work Without Permit":173,"Other":358},{"communityBoard":"411","count":986,"Building Maintenance":85,"Elevator Maintenance":9,"Failure to Comply":126,"Miscellaneous":145,"Work Without Permit":119,"Other":502},{"communityBoard":"412","count":2235,"Building Maintenance":192,"Elevator Maintenance":105,"Failure to Comply":668,"Miscellaneous":185,"Work Without Permit":247,"Other":838},{"communityBoard":"413","count":1321,"Building Maintenance":101,"Elevator Maintenance":9,"Failure to Comply":473,"Miscellaneous":95,"Work Without Permit":178,"Other":465},{"communityBoard":"414","count":735,"Building Maintenance":88,"Elevator Maintenance":48,"Failure to Comply":127,"Miscellaneous":67,"Work Without Permit":69,"Other":336},{"communityBoard":"480","count":0,"Building Maintenance":0,"Elevator Maintenance":0,"Failure to Comply":0,"Miscellaneous":0,"Work Without Permit":0,"Other":0},{"communityBoard":"481","count":4,"Building Maintenance":0,"Elevator Maintenance":3,"Failure to Comply":0,"Miscellaneous":0,"Work Without Permit":0,"Other":1},{"communityBoard":"482","count":0,"Building Maintenance":0,"Elevator Maintenance":0,"Failure to Comply":0,"Miscellaneous":0,"Work Without Permit":0,"Other":0},{"communityBoard":"483","count":1,"Building Maintenance":0,"Elevator Maintenance":0,"Failure to Comply":0,"Miscellaneous":0,"Work Without Permit":0,"Other":1},{"communityBoard":"484","count":0,"Building Maintenance":0,"Elevator Maintenance":0,"Failure to Comply":0,"Miscellaneous":0,"Work Without Permit":0,"Other":0},{"communityBoard":"501","count":1244,"Building Maintenance":113,"Elevator Maintenance":41,"Failure to Comply":356,"Miscellaneous":85,"Work Without Permit":157,"Other":492},{"communityBoard":"502","count":650,"Building Maintenance":50,"Elevator Maintenance":6,"Failure to Comply":86,"Miscellaneous":85,"Work Without Permit":103,"Other":320},{"communityBoard":"503","count":650,"Building Maintenance":73,"Elevator Maintenance":7,"Failure to Comply":91,"Miscellaneous":80,"Work Without Permit":70,"Other":329},{"communityBoard":"595","count":0,"Building Maintenance":0,"Elevator Maintenance":0,"Failure to Comply":0,"Miscellaneous":0,"Work Without Permit":0,"Other":0}]