[
 {
	"values": 
	[
		{		
		"x": "Bronx",
		"y": 1
		},
		 {		
		"x": "Brooklyn",
		"y": 1
		},
		 {		
		"x": "Queens",
		"y": 1
		},
		 {		
		"x": "Manhattan",
		"y": 1
		},
		 {		
		"x": "Staten Island",
		"y": 0
		} 
	],
	"key": "Emergency Work"
 },
 {
	"values": 
	[
		{		
		"x": "Staten Island",
		"y": 7
		}
,
		 {		
		"x": "Queens",
		"y": 63
		},
		 {		
		"x": "Brooklyn",
		"y": 80
		},
		 {		
		"x": "Manhattan",
		"y": 178
		},
		 {		
		"x": "Bronx",
		"y": 45
		} 
	],
	"key": "Minimal Noise"
 },
 {
	"values": 
	[
		{		
		"x": "Brooklyn",
		"y": 75
		}
,
		 {		
		"x": "Queens",
		"y": 23
		},
		 {		
		"x": "Manhattan",
		"y": 35
		},
		 {		
		"x": "Staten Island",
		"y": 8
		},
		 {		
		"x": "Bronx",
		"y": 30
		} 
	],
	"key": "NYC Construction"
 },
 {
	"values": 
	[
		{		
		"x": "Queens",
		"y": 69
		}
,
		 {		
		"x": "Brooklyn",
		"y": 84
		},
		 {		
		"x": "Staten Island",
		"y": 3
		},
		 {		
		"x": "Manhattan",
		"y": 367
		},
		 {		
		"x": "Bronx",
		"y": 52
		} 
	],
	"key": "Public Safety"
 },
 {
	"values": 
	[
		{		
		"x": "Brooklyn",
		"y": 20
		}
,
		 {		
		"x": "Queens",
		"y": 13
		},
		 {		
		"x": "Manhattan",
		"y": 16
		},
		 {		
		"x": "Bronx",
		"y": 1
		},
		 {		
		"x": "Staten Island",
		"y": 0
		}
	],
	"key": "Undue Hardship"
 }
]