[
 {
	"count": 3078,
	"communityBoard": "104",
	"After Hours Work": 62,
	"Elevator": 173,
	"Illegal Conversion": 119,
	"Other": 2626,
	"Work Without Permit": 98
 },
 {
	"count": 2099,
	"communityBoard": "109",
	"After Hours Work": 42,
	"Elevator": 405,
	"Illegal Conversion": 147,
	"Other": 1440,
	"Work Without Permit": 65
 },
 {
	"count": 3858,
	"communityBoard": "307",
	"After Hours Work": 40,
	"Elevator": 177,
	"Illegal Conversion": 560,
	"Other": 2537,
	"Work Without Permit": 544
 },
 {
	"count": 2759,
	"communityBoard": "308",
	"After Hours Work": 52,
	"Elevator": 80,
	"Illegal Conversion": 242,
	"Other": 2105,
	"Work Without Permit": 280
 },
 {
	"count": 2496,
	"communityBoard": "309",
	"After Hours Work": 57,
	"Elevator": 373,
	"Illegal Conversion": 184,
	"Other": 1620,
	"Work Without Permit": 262
 },
 {
	"count": 3596,
	"communityBoard": "317",
	"After Hours Work": 56,
	"Elevator": 300,
	"Illegal Conversion": 703,
	"Other": 2073,
	"Work Without Permit": 464
 },
 {
	"count": 3532,
	"communityBoard": "318",
	"After Hours Work": 26,
	"Elevator": 59,
	"Illegal Conversion": 862,
	"Other": 1719,
	"Work Without Permit": 866
 },
 {
	"count": 6065,
	"communityBoard": "407",
	"After Hours Work": 83,
	"Elevator": 207,
	"Illegal Conversion": 1529,
	"Other": 3440,
	"Work Without Permit": 806
 },
 {
	"count": 3446,
	"communityBoard": "408",
	"After Hours Work": 54,
	"Elevator": 119,
	"Illegal Conversion": 763,
	"Other": 1935,
	"Work Without Permit": 575
 },
 {
	"count": 3852,
	"communityBoard": "409",
	"After Hours Work": 36,
	"Elevator": 73,
	"Illegal Conversion": 1607,
	"Other": 1548,
	"Work Without Permit": 588
 },
 {
	"count": 5046,
	"communityBoard": "410",
	"After Hours Work": 22,
	"Elevator": 11,
	"Illegal Conversion": 2391,
	"Other": 1714,
	"Work Without Permit": 908
 },
 {
	"count": 2955,
	"communityBoard": "411",
	"After Hours Work": 64,
	"Elevator": 19,
	"Illegal Conversion": 584,
	"Other": 1634,
	"Work Without Permit": 654
 },
 {
	"count": 5802,
	"communityBoard": "412",
	"After Hours Work": 33,
	"Elevator": 215,
	"Illegal Conversion": 1848,
	"Other": 2939,
	"Work Without Permit": 767
 },
 {
	"count": 2032,
	"communityBoard": "414",
	"After Hours Work": 15,
	"Elevator": 225,
	"Illegal Conversion": 301,
	"Other": 1200,
	"Work Without Permit": 291
 },
 {
	"count": 3,
	"communityBoard": "595",
	"After Hours Work": 0,
	"Elevator": 0,
	"Illegal Conversion": 0,
	"Other": 3,
	"Work Without Permit": 0
 },
 {
	"count": 3893,
	"communityBoard": "103",
	"After Hours Work": 93,
	"Elevator": 229,
	"Illegal Conversion": 326,
	"Other": 3108,
	"Work Without Permit": 137
 },
 {
	"count": 3264,
	"communityBoard": "105",
	"After Hours Work": 81,
	"Elevator": 266,
	"Illegal Conversion": 91,
	"Other": 2678,
	"Work Without Permit": 148
 },
 {
	"count": 3899,
	"communityBoard": "108",
	"After Hours Work": 115,
	"Elevator": 277,
	"Illegal Conversion": 141,
	"Other": 3281,
	"Work Without Permit": 85
 },
 {
	"count": 1592,
	"communityBoard": "201",
	"After Hours Work": 14,
	"Elevator": 259,
	"Illegal Conversion": 101,
	"Other": 1163,
	"Work Without Permit": 55
 },
 {
	"count": 8104,
	"communityBoard": "301",
	"After Hours Work": 174,
	"Elevator": 294,
	"Illegal Conversion": 366,
	"Other": 6493,
	"Work Without Permit": 777
 },
 {
	"count": 3460,
	"communityBoard": "310",
	"After Hours Work": 32,
	"Elevator": 180,
	"Illegal Conversion": 647,
	"Other": 1819,
	"Work Without Permit": 782
 },
 {
	"count": 4574,
	"communityBoard": "312",
	"After Hours Work": 92,
	"Elevator": 141,
	"Illegal Conversion": 555,
	"Other": 3232,
	"Work Without Permit": 554
 },
 {
	"count": 2909,
	"communityBoard": "403",
	"After Hours Work": 26,
	"Elevator": 191,
	"Illegal Conversion": 780,
	"Other": 1565,
	"Work Without Permit": 347
 },
 {
	"count": 4731,
	"communityBoard": "405",
	"After Hours Work": 97,
	"Elevator": 27,
	"Illegal Conversion": 1157,
	"Other": 2534,
	"Work Without Permit": 916
 },
 {
	"count": 3802,
	"communityBoard": "413",
	"After Hours Work": 37,
	"Elevator": 7,
	"Illegal Conversion": 1333,
	"Other": 1687,
	"Work Without Permit": 738
 },
 {
	"count": 1,
	"communityBoard": "480",
	"After Hours Work": 0,
	"Elevator": 0,
	"Illegal Conversion": 0,
	"Other": 1,
	"Work Without Permit": 0
 },
 {
	"count": 0,
	"communityBoard": "356",
	"After Hours Work": 0,
	"Elevator": 0,
	"Illegal Conversion": 0,
	"Other": 0,
	"Work Without Permit": 0
 },
 {
	"count": 2354,
	"communityBoard": "106",
	"After Hours Work": 65,
	"Elevator": 196,
	"Illegal Conversion": 78,
	"Other": 1960,
	"Work Without Permit": 55
 },
 {
	"count": 3734,
	"communityBoard": "107",
	"After Hours Work": 113,
	"Elevator": 374,
	"Illegal Conversion": 179,
	"Other": 2975,
	"Work Without Permit": 93
 },
 {
	"count": 2650,
	"communityBoard": "112",
	"After Hours Work": 67,
	"Elevator": 460,
	"Illegal Conversion": 233,
	"Other": 1819,
	"Work Without Permit": 71
 },
 {
	"count": 843,
	"communityBoard": "202",
	"After Hours Work": 9,
	"Elevator": 178,
	"Illegal Conversion": 74,
	"Other": 548,
	"Work Without Permit": 34
 },
 {
	"count": 1798,
	"communityBoard": "206",
	"After Hours Work": 18,
	"Elevator": 285,
	"Illegal Conversion": 208,
	"Other": 1211,
	"Work Without Permit": 76
 },
 {
	"count": 4352,
	"communityBoard": "302",
	"After Hours Work": 95,
	"Elevator": 167,
	"Illegal Conversion": 93,
	"Other": 3746,
	"Work Without Permit": 251
 },
 {
	"count": 5326,
	"communityBoard": "303",
	"After Hours Work": 99,
	"Elevator": 167,
	"Illegal Conversion": 425,
	"Other": 4122,
	"Work Without Permit": 513
 },
 {
	"count": 3382,
	"communityBoard": "311",
	"After Hours Work": 47,
	"Elevator": 82,
	"Illegal Conversion": 670,
	"Other": 2080,
	"Work Without Permit": 503
 },
 {
	"count": 1882,
	"communityBoard": "313",
	"After Hours Work": 19,
	"Elevator": 166,
	"Illegal Conversion": 213,
	"Other": 1295,
	"Work Without Permit": 189
 },
 {
	"count": 9,
	"communityBoard": "355",
	"After Hours Work": 0,
	"Elevator": 1,
	"Illegal Conversion": 0,
	"Other": 6,
	"Work Without Permit": 2
 },
 {
	"count": 2504,
	"communityBoard": "404",
	"After Hours Work": 17,
	"Elevator": 174,
	"Illegal Conversion": 741,
	"Other": 1378,
	"Work Without Permit": 194
 },
 {
	"count": 1952,
	"communityBoard": "406",
	"After Hours Work": 31,
	"Elevator": 217,
	"Illegal Conversion": 214,
	"Other": 1206,
	"Work Without Permit": 284
 },
 {
	"count": 2761,
	"communityBoard": "502",
	"After Hours Work": 45,
	"Elevator": 32,
	"Illegal Conversion": 443,
	"Other": 1711,
	"Work Without Permit": 530
 },
 {
	"count": 0,
	"communityBoard": "228",
	"After Hours Work": 0,
	"Elevator": 0,
	"Illegal Conversion": 0,
	"Other": 0,
	"Work Without Permit": 0
 },
 {
	"count": 12,
	"communityBoard": "226",
	"After Hours Work": 0,
	"Elevator": 0,
	"Illegal Conversion": 0,
	"Other": 12,
	"Work Without Permit": 0
 },
 {
	"count": 1867,
	"communityBoard": "101",
	"After Hours Work": 51,
	"Elevator": 131,
	"Illegal Conversion": 41,
	"Other": 1577,
	"Work Without Permit": 67
 },
 {
	"count": 3342,
	"communityBoard": "102",
	"After Hours Work": 83,
	"Elevator": 89,
	"Illegal Conversion": 151,
	"Other": 2856,
	"Work Without Permit": 163
 },
 {
	"count": 2847,
	"communityBoard": "110",
	"After Hours Work": 47,
	"Elevator": 533,
	"Illegal Conversion": 191,
	"Other": 2007,
	"Work Without Permit": 69
 },
 {
	"count": 1819,
	"communityBoard": "111",
	"After Hours Work": 26,
	"Elevator": 266,
	"Illegal Conversion": 110,
	"Other": 1365,
	"Work Without Permit": 52
 },
 {
	"count": 1340,
	"communityBoard": "203",
	"After Hours Work": 19,
	"Elevator": 257,
	"Illegal Conversion": 128,
	"Other": 907,
	"Work Without Permit": 29
 },
 {
	"count": 2316,
	"communityBoard": "204",
	"After Hours Work": 16,
	"Elevator": 636,
	"Illegal Conversion": 226,
	"Other": 1390,
	"Work Without Permit": 48
 },
 {
	"count": 2203,
	"communityBoard": "205",
	"After Hours Work": 14,
	"Elevator": 647,
	"Illegal Conversion": 233,
	"Other": 1247,
	"Work Without Permit": 62
 },
 {
	"count": 2131,
	"communityBoard": "207",
	"After Hours Work": 24,
	"Elevator": 564,
	"Illegal Conversion": 216,
	"Other": 1235,
	"Work Without Permit": 92
 },
 {
	"count": 1566,
	"communityBoard": "208",
	"After Hours Work": 35,
	"Elevator": 210,
	"Illegal Conversion": 108,
	"Other": 1040,
	"Work Without Permit": 173
 },
 {
	"count": 2639,
	"communityBoard": "209",
	"After Hours Work": 23,
	"Elevator": 509,
	"Illegal Conversion": 606,
	"Other": 1317,
	"Work Without Permit": 184
 },
 {
	"count": 1909,
	"communityBoard": "210",
	"After Hours Work": 18,
	"Elevator": 82,
	"Illegal Conversion": 577,
	"Other": 943,
	"Work Without Permit": 289
 },
 {
	"count": 1868,
	"communityBoard": "211",
	"After Hours Work": 18,
	"Elevator": 220,
	"Illegal Conversion": 399,
	"Other": 946,
	"Work Without Permit": 285
 },
 {
	"count": 2500,
	"communityBoard": "212",
	"After Hours Work": 21,
	"Elevator": 190,
	"Illegal Conversion": 654,
	"Other": 1465,
	"Work Without Permit": 170
 },
 {
	"count": 3581,
	"communityBoard": "304",
	"After Hours Work": 58,
	"Elevator": 61,
	"Illegal Conversion": 480,
	"Other": 2631,
	"Work Without Permit": 351
 },
 {
	"count": 4712,
	"communityBoard": "305",
	"After Hours Work": 47,
	"Elevator": 160,
	"Illegal Conversion": 857,
	"Other": 3102,
	"Work Without Permit": 546
 },
 {
	"count": 3522,
	"communityBoard": "306",
	"After Hours Work": 93,
	"Elevator": 62,
	"Illegal Conversion": 121,
	"Other": 2940,
	"Work Without Permit": 306
 },
 {
	"count": 3136,
	"communityBoard": "314",
	"After Hours Work": 45,
	"Elevator": 551,
	"Illegal Conversion": 354,
	"Other": 1765,
	"Work Without Permit": 421
 },
 {
	"count": 3680,
	"communityBoard": "315",
	"After Hours Work": 61,
	"Elevator": 341,
	"Illegal Conversion": 444,
	"Other": 2278,
	"Work Without Permit": 556
 },
 {
	"count": 1696,
	"communityBoard": "316",
	"After Hours Work": 7,
	"Elevator": 99,
	"Illegal Conversion": 321,
	"Other": 1148,
	"Work Without Permit": 121
 },
 {
	"count": 4456,
	"communityBoard": "401",
	"After Hours Work": 100,
	"Elevator": 114,
	"Illegal Conversion": 700,
	"Other": 3104,
	"Work Without Permit": 438
 },
 {
	"count": 2876,
	"communityBoard": "402",
	"After Hours Work": 56,
	"Elevator": 141,
	"Illegal Conversion": 478,
	"Other": 1889,
	"Work Without Permit": 312
 },
 {
	"count": 3659,
	"communityBoard": "501",
	"After Hours Work": 37,
	"Elevator": 133,
	"Illegal Conversion": 798,
	"Other": 2129,
	"Work Without Permit": 562
 },
 {
	"count": 2925,
	"communityBoard": "503",
	"After Hours Work": 46,
	"Elevator": 10,
	"Illegal Conversion": 421,
	"Other": 1871,
	"Work Without Permit": 577
 },
 {
	"count": 1,
	"communityBoard": "227",
	"After Hours Work": 0,
	"Elevator": 1,
	"Illegal Conversion": 0,
	"Other": 0,
	"Work Without Permit": 0
 },
 {
	"count": 17,
	"communityBoard": "164",
	"After Hours Work": 0,
	"Elevator": 0,
	"Illegal Conversion": 0,
	"Other": 17,
	"Work Without Permit": 0
 },
 {
	"count": 4,
	"communityBoard": "481",
	"After Hours Work": 0,
	"Elevator": 0,
	"Illegal Conversion": 0,
	"Other": 4,
	"Work Without Permit": 0
 },
 {
	"count": 0,
	"communityBoard": "484",
	"After Hours Work": 0,
	"Elevator": 0,
	"Illegal Conversion": 0,
	"Other": 0,
	"Work Without Permit": 0
 },
 {
	"count": 3,
	"communityBoard": "482",
	"After Hours Work": 0,
	"Elevator": 1,
	"Illegal Conversion": 0,
	"Other": 2,
	"Work Without Permit": 0
 },
 {
	"count": 2,
	"communityBoard": "483",
	"After Hours Work": 0,
	"Elevator": 0,
	"Illegal Conversion": 0,
	"Other": 2,
	"Work Without Permit": 0
 }
]