[{"count":1464,"communityBoard":"101","After Hours Work":92,"Elevator":219,"Illegal Conversion":11,"Work Without Permit":121,"Other":1021},{"count":2228,"communityBoard":"102","After Hours Work":118,"Elevator":97,"Illegal Conversion":46,"Work Without Permit":269,"Other":1698},{"count":2631,"communityBoard":"103","After Hours Work":106,"Elevator":155,"Illegal Conversion":121,"Work Without Permit":302,"Other":1947},{"count":2547,"communityBoard":"104","After Hours Work":124,"Elevator":232,"Illegal Conversion":74,"Work Without Permit":234,"Other":1883},{"count":2556,"communityBoard":"105","After Hours Work":134,"Elevator":303,"Illegal Conversion":39,"Work Without Permit":171,"Other":1909},{"count":1819,"communityBoard":"106","After Hours Work":90,"Elevator":213,"Illegal Conversion":43,"Work Without Permit":175,"Other":1298},{"count":2851,"communityBoard":"107","After Hours Work":151,"Elevator":372,"Illegal Conversion":66,"Work Without Permit":321,"Other":1941},{"count":2712,"communityBoard":"108","After Hours Work":128,"Elevator":215,"Illegal Conversion":52,"Work Without Permit":289,"Other":2028},{"count":1461,"communityBoard":"109","After Hours Work":38,"Elevator":392,"Illegal Conversion":61,"Work Without Permit":135,"Other":835},{"count":2113,"communityBoard":"110","After Hours Work":60,"Elevator":643,"Illegal Conversion":71,"Work Without Permit":176,"Other":1163},{"count":1432,"communityBoard":"111","After Hours Work":34,"Elevator":353,"Illegal Conversion":46,"Work Without Permit":131,"Other":868},{"count":2038,"communityBoard":"112","After Hours Work":47,"Elevator":670,"Illegal Conversion":109,"Work Without Permit":202,"Other":1010},{"count":4,"communityBoard":"164","After Hours Work":0,"Elevator":1,"Illegal Conversion":0,"Work Without Permit":1,"Other":2},{"count":1095,"communityBoard":"201","After Hours Work":11,"Elevator":264,"Illegal Conversion":37,"Work Without Permit":53,"Other":730},{"count":675,"communityBoard":"202","After Hours Work":6,"Elevator":152,"Illegal Conversion":38,"Work Without Permit":50,"Other":429},{"count":955,"communityBoard":"203","After Hours Work":8,"Elevator":234,"Illegal Conversion":48,"Work Without Permit":48,"Other":617},{"count":1623,"communityBoard":"204","After Hours Work":20,"Elevator":652,"Illegal Conversion":63,"Work Without Permit":117,"Other":771},{"count":1494,"communityBoard":"205","After Hours Work":18,"Elevator":552,"Illegal Conversion":99,"Work Without Permit":77,"Other":748},{"count":1034,"communityBoard":"206","After Hours Work":15,"Elevator":290,"Illegal Conversion":65,"Work Without Permit":51,"Other":613},{"count":1446,"communityBoard":"207","After Hours Work":20,"Elevator":437,"Illegal Conversion":132,"Work Without Permit":92,"Other":765},{"count":1082,"communityBoard":"208","After Hours Work":32,"Elevator":221,"Illegal Conversion":43,"Work Without Permit":115,"Other":671},{"count":1650,"communityBoard":"209","After Hours Work":31,"Elevator":520,"Illegal Conversion":220,"Work Without Permit":140,"Other":739},{"count":1096,"communityBoard":"210","After Hours Work":16,"Elevator":54,"Illegal Conversion":170,"Work Without Permit":170,"Other":686},{"count":1150,"communityBoard":"211","After Hours Work":13,"Elevator":195,"Illegal Conversion":177,"Work Without Permit":147,"Other":618},{"count":1511,"communityBoard":"212","After Hours Work":26,"Elevator":178,"Illegal Conversion":249,"Work Without Permit":153,"Other":905},{"count":3,"communityBoard":"226","After Hours Work":0,"Elevator":0,"Illegal Conversion":0,"Work Without Permit":1,"Other":2},{"count":2,"communityBoard":"227","After Hours Work":0,"Elevator":0,"Illegal Conversion":0,"Work Without Permit":1,"Other":1},{"count":0,"communityBoard":"228","After Hours Work":0,"Elevator":0,"Illegal Conversion":0,"Work Without Permit":0,"Other":0},{"count":4265,"communityBoard":"301","After Hours Work":159,"Elevator":283,"Illegal Conversion":148,"Work Without Permit":513,"Other":3162},{"count":2286,"communityBoard":"302","After Hours Work":144,"Elevator":147,"Illegal Conversion":46,"Work Without Permit":244,"Other":1705},{"count":3544,"communityBoard":"303","After Hours Work":130,"Elevator":153,"Illegal Conversion":165,"Work Without Permit":502,"Other":2594},{"count":2252,"communityBoard":"304","After Hours Work":54,"Elevator":54,"Illegal Conversion":172,"Work Without Permit":316,"Other":1656},{"count":2176,"communityBoard":"305","After Hours Work":40,"Elevator":291,"Illegal Conversion":325,"Work Without Permit":297,"Other":1223},{"count":2033,"communityBoard":"306","After Hours Work":90,"Elevator":80,"Illegal Conversion":39,"Work Without Permit":294,"Other":1530},{"count":1687,"communityBoard":"307","After Hours Work":62,"Elevator":89,"Illegal Conversion":198,"Work Without Permit":249,"Other":1089},{"count":1846,"communityBoard":"308","After Hours Work":97,"Elevator":142,"Illegal Conversion":64,"Work Without Permit":260,"Other":1283},{"count":1684,"communityBoard":"309","After Hours Work":38,"Elevator":336,"Illegal Conversion":73,"Work Without Permit":217,"Other":1020},{"count":2031,"communityBoard":"310","After Hours Work":59,"Elevator":145,"Illegal Conversion":306,"Work Without Permit":404,"Other":1117},{"count":2207,"communityBoard":"311","After Hours Work":74,"Elevator":97,"Illegal Conversion":274,"Work Without Permit":353,"Other":1409},{"count":2595,"communityBoard":"312","After Hours Work":88,"Elevator":194,"Illegal Conversion":177,"Work Without Permit":400,"Other":1736},{"count":1238,"communityBoard":"313","After Hours Work":28,"Elevator":166,"Illegal Conversion":94,"Work Without Permit":149,"Other":801},{"count":2220,"communityBoard":"314","After Hours Work":70,"Elevator":521,"Illegal Conversion":121,"Work Without Permit":314,"Other":1194},{"count":2297,"communityBoard":"315","After Hours Work":56,"Elevator":332,"Illegal Conversion":168,"Work Without Permit":397,"Other":1344},{"count":1099,"communityBoard":"316","After Hours Work":16,"Elevator":112,"Illegal Conversion":90,"Work Without Permit":115,"Other":766},{"count":2177,"communityBoard":"317","After Hours Work":66,"Elevator":328,"Illegal Conversion":186,"Work Without Permit":179,"Other":1418},{"count":1687,"communityBoard":"318","After Hours Work":30,"Elevator":94,"Illegal Conversion":253,"Work Without Permit":295,"Other":1015},{"count":4,"communityBoard":"355","After Hours Work":0,"Elevator":1,"Illegal Conversion":2,"Work Without Permit":0,"Other":1},{"count":1,"communityBoard":"356","After Hours Work":0,"Elevator":0,"Illegal Conversion":0,"Work Without Permit":0,"Other":1},{"count":2502,"communityBoard":"401","After Hours Work":86,"Elevator":117,"Illegal Conversion":233,"Work Without Permit":351,"Other":1715},{"count":1710,"communityBoard":"402","After Hours Work":70,"Elevator":149,"Illegal Conversion":158,"Work Without Permit":226,"Other":1107},{"count":1479,"communityBoard":"403","After Hours Work":17,"Elevator":213,"Illegal Conversion":279,"Work Without Permit":196,"Other":774},{"count":1290,"communityBoard":"404","After Hours Work":26,"Elevator":151,"Illegal Conversion":206,"Work Without Permit":158,"Other":749},{"count":2094,"communityBoard":"405","After Hours Work":62,"Elevator":13,"Illegal Conversion":389,"Work Without Permit":407,"Other":1223},{"count":1182,"communityBoard":"406","After Hours Work":46,"Elevator":283,"Illegal Conversion":90,"Work Without Permit":139,"Other":624},{"count":3059,"communityBoard":"407","After Hours Work":107,"Elevator":253,"Illegal Conversion":542,"Work Without Permit":347,"Other":1810},{"count":1724,"communityBoard":"408","After Hours Work":41,"Elevator":142,"Illegal Conversion":259,"Work Without Permit":217,"Other":1065},{"count":2046,"communityBoard":"409","After Hours Work":30,"Elevator":70,"Illegal Conversion":614,"Work Without Permit":294,"Other":1038},{"count":2031,"communityBoard":"410","After Hours Work":33,"Elevator":15,"Illegal Conversion":682,"Work Without Permit":350,"Other":951},{"count":1330,"communityBoard":"411","After Hours Work":59,"Elevator":19,"Illegal Conversion":217,"Work Without Permit":214,"Other":821},{"count":3186,"communityBoard":"412","After Hours Work":46,"Elevator":191,"Illegal Conversion":728,"Work Without Permit":355,"Other":1866},{"count":1826,"communityBoard":"413","After Hours Work":19,"Elevator":13,"Illegal Conversion":434,"Work Without Permit":218,"Other":1142},{"count":1280,"communityBoard":"414","After Hours Work":14,"Elevator":213,"Illegal Conversion":116,"Work Without Permit":170,"Other":767},{"count":0,"communityBoard":"480","After Hours Work":0,"Elevator":0,"Illegal Conversion":0,"Work Without Permit":0,"Other":0},{"count":8,"communityBoard":"481","After Hours Work":0,"Elevator":3,"Illegal Conversion":0,"Work Without Permit":0,"Other":5},{"count":0,"communityBoard":"482","After Hours Work":0,"Elevator":0,"Illegal Conversion":0,"Work Without Permit":0,"Other":0},{"count":0,"communityBoard":"483","After Hours Work":0,"Elevator":0,"Illegal Conversion":0,"Work Without Permit":0,"Other":0},{"count":3,"communityBoard":"484","After Hours Work":0,"Elevator":0,"Illegal Conversion":0,"Work Without Permit":2,"Other":1},{"count":2002,"communityBoard":"501","After Hours Work":37,"Elevator":135,"Illegal Conversion":275,"Work Without Permit":324,"Other":1231},{"count":1333,"communityBoard":"502","After Hours Work":57,"Elevator":21,"Illegal Conversion":158,"Work Without Permit":255,"Other":842},{"count":1457,"communityBoard":"503","After Hours Work":31,"Elevator":12,"Illegal Conversion":125,"Work Without Permit":271,"Other":1018},{"count":2,"communityBoard":"595","After Hours Work":0,"Elevator":0,"Illegal Conversion":0,"Work Without Permit":0,"Other":2}]